{
    "adygea":[
      "Адыгейск",
      "Майкоп"
    ],
    "bashkortostan":[
      "Агидель",
      "Амзинский",
      "Сельсовет",
      "Кумертау",
      "Маячинский",
      "Межгорье",
      "Нефтекамск",
      "Октябрьский",
      "Подгорный",
      "Салават",
      "Сибай",
      "Стерлитамак",
      "Ташкиновский",
      "Туялясский",
      "Уфа"
    ],
    "buryatia":[
      "Северобайкальск",
      "Улан-Удэ"
    ],
    "altay":[
      "Горно-Алтайск"
    ],
    "dagestan":[
      "Буйнакск",
      "Дагестанские Огни",
      "Дербент",
      "Избербаш",
      "Каспийск",
      "Кизилюрт",
      "Кизляр",
      "Махачкала",
      "Хасавюрт",
      "Южно-Сухокумск"
    ],
    "ingushetia":[
      "Карабулак",
      "Магас",
      "Малгобек",
      "Назрань",
      "Сунжа"
    ],
    "dnr":[
      "Авдеевка",
      "Амвросиевка",
      "Волноваха",
      "Горловка",
      "Дебальцево",
      "Докучаевск",
      "Ждановка",
      "Кировское",
      "Макеевка",
      "Мариуполь",
      "Новоазовск",
      "Снежное",
      "Старобешево",
      "Тельманово",
      "Торез",
      "Углегорск",
      "Шахтерск",
      "Ясиноватая"
    ],
    "kabardino-balkaria":[
      "Баксан",
      "Нальчик",
      "Прохладный"
    ],
    "kalmykia":[
      "Элиста"
    ],
    "karachay-cherkessia":[
      "Карачаевск",
      "Теберда",
      "Черкесск"
    ],
    "karelia":[
      "Костомукша",
      "Петрозаводск",
      "Сортавала",
      ""
    ],
    "komi":[
      "Воркута",
      "Вуктыл",
      "Инта",
      "Печора",
      "Сосногорск",
      "Сыктывкар",
      "Усинск",
      "Ухта"
    ],
    "mariy-el":[
      "Волжск",
      "Йошкар-Ола",
      "Козьмодемьянск"
    ],
    "mordovia":[
      "Ковылкино",
      "Рузаевка",
      "Саранск"
    ],
    "saha":[
      "Якутск"
    ],
    "alanya":[
      "Владикавказ"
    ],
    "tatarstan":[
      "Казань",
      "Набережные Челны"
    ],
    "tuva":[
      "Ак-Довурак",
      "Кызыл"
    ],
    "udmurtia":[
      "Воткинск",
      "Глазов",
      "Ижевск",
      "Можга",
      "Сарапул"
    ],
    "hakasia":[
      "Абаза",
      "Абакан",
      "Саяногорск",
      "Сорск",
      "Черногорск"
    ],
    "сhechnya":[
      "Аргун",
      "Грозный"
    ],
    "сhuvashia":[
      "Алатырь",
      "Канаш",
      "Новочебоксарск",
      "Чебоксары",
      "Шумерля"
    ],
    "altai":[
      "Алейск",
      "Барнаул",
      "Белокуриха",
      "Бийск",
      "Заринск",
      "Новоалтайск",
      "Рубцовск",
      "Славгород",
      "Яровое"
    ],
    "krasnodarskiy":[
      "Армавир",
      "Геленджик",
      "Горячий",
      "Ключ",
      "Краснодар",
      "Новороссийск",
      "Сириус",
      "Сочи"
    ],
    "krasnoyarskiy":[
      "Ачинск",
      "Боготол",
      "Бородино",
      "Дивногорск",
      "Енисейск",
      "Железногорск",
      "Зеленогорск",
      "Канск",
      "Кедровый",
      "Красноярск",
      "Лесосибирск",
      "Минусинск",
      "Назарово",
      "Норильск",
      "Подгорный",
      "Солнечный",
      "Сосновоборск",
      "Шарыпово"
    ],
    "primorskiy":[
      "Арсеньев",
      "Артем",
      "Большой",
      "Камень",
      "Владивосток",
      "Дальнегорск",
      "Дальнереченск",
      "Лесозаводск",
      "Находка",
      "Партизанск",
      "Спасск-Дальний",
      "Уссурийск",
      "Фокино"
    ],
    "stavropolskiy":[
      "Георгиевск",
      "Ессентуки",
      "Железноводск",
      "Кисловодск",
      "Лермонтов",
      "Невинномысск",
      "Пятигорск",
      "Ставрополь"
    ],
    "khabarovkiy":[
      "Амурск",
      "Бикин",
      "Комсомольск-на-Амуре",
      "Николаевск-на-Амуре",
      "Советская Гавань",
      "Хабаровск"
    ],
    "amurskaya":[
      "Белогорск",
      "Белогорск",
      "Город",
      "Благовещенск",
      "Зея",
      "Прогресс",
      "Райчихинск",
      "Свободный",
      "Тында",
      "Циолковский",
      "Шимановск"
    ],
    "arkhangelskay":[
      "Архангельск",
      "Коряжма",
      "Мирный",
      "Новодвинск",
      "Северодвинск"
    ],
    "astrakhanskaya":[
      "Астрахань",
      "Знаменск"
    ],
    "belgorodskaya":[
      "Белгород",
      "Губкин",
      "Старый",
      "Оскол",
      "Шебекино"
    ],
    "bryanskaya":[
      "Брянск",
      "Клинцы",
      "Новозыбков",
      "Сельцо",
      "Стародуб",
      "Фокино"
    ],
    "vladimirskaya":[
      "Владимир",
      "Гусь-Хрустальный",
      "Ковров",
      "Муром",
      "Радужный"
    ],
    "volgogradskaya":[
      "Волгоград",
      "Волжский",
      "Камышин",
      "Михайловка",
      "Урюпинск",
      "Фролово"
    ],
    "vologodskaya":[
      "Вологда",
      "Череповец"
    ],
    "voronezhskaya":[
      "Воронеж",
      "Воронеж-45",
      "Нововоронеж"
    ],
    "ivanovskaya":[
      "Иваново",
      "Кинешма"
    ],
    "irkutskaya":[
      "Бодайбо",
      "Братск",
      "Зима",
      "Иркутск",
      "Нижнеудинск",
      "Саянск",
      "Свирск",
      "Тайшет",
      "Тулун",
      "Усолье-Сибирское",
      "Усть-Илимск",
      "Усть-Кут",
      "Черемхово",
      "Шелехов"
    ],
    "kaliningradskaya":[
      "Калининград",
      "Ладушкин",
      "Мамоново",
      "Пионерский",
      "Светлый",
      "Советск",
      "Янтарный"
    ],
    "kaluzhskaya":[
      "Калуга",
      "Обнинск"
    ],
    "kamchatskiy":[
      "Вилючинск",
      "Петропавловск-Камчатский"
    ],
    "kemerovskaya":[
      "Анжеро-Судженск",
      "Белово",
      "Березовский",
      "Калтан",
      "Кемерово",
      "Киселевск",
      "Краснобродский",
      "Ленинск-Кузнецкий",
      "Междуреченск",
      "Мыски",
      "Новокузнецк",
      "Осинники",
      "Полысаево",
      "Прокопьевск",
      "Тайга",
      "Юрга"
    ],
    "kirovskaya":[
      "Киров",
      "Кирово-Чепецк",
      "Первомайский"
    ],
    "kostromskaya":[
      "Волгореченск",
      "Кострома"
    ],
    "kurganskaya":[
      "Курган",
      "Шадринск"
    ],
    "kurskaya":[
      "Железногорск",
      "Курск",
      "Курчатов",
      "Льгов",
      "Щигры"
    ],
    "leningradskaya":[
      "Зеленогорск",
      "Колпино",
      "Красное Село",
      "Кронштадт",
      "Ломоносов",
      "Павловск",
      "Петергоф",
      "Пушкин",
      "Санкт-Петербург",
      "Сестрорецк ",
      "Сосновый Бор"
    ],
    "lipetskaya":[
      "Елец",
      "Липецк"
    ],
    "magadanskaya":[
      "Магадан"
    ],
    "moskovskaya":[
      "Балашиха",
      "Бронницы",
      "Видное",
      "Волоколамск",
      "Дзержинский",
      "Долгопрудный",
      "Домодедово",
      "Дубна",
      "Егорьевск",
      "Жуковский",
      "Зарайск",
      "Кашира",
      "Королёв",
      "Котельники",
      "Красногорск",
      "Краснознаменск",
      "Лобня",
      "Лосино-Петровский",
      "Лотошино",
      "Рабочий",
      "поселок",
      "Луховицы",
      "Лыткарино",
      "Люберцы",
      "Можайск",
      "Мытищи",
      "Павловский",
      "Посад",
      "Подольск",
      "Протвино",
      "Пущино",
      "Раменское",
      "Реутов",
      "Руза",
      "Серебряные",
      "Пруды",
      "Серпухов",
      "Солнечногорск",
      "Ступино",
      "Талдом",
      "Фрязино",
      "Химки",
      "Черноголовка",
      "Чехов",
      "Шаховская",
      "Щёлково",
      "Электрогорск",
      "Электросталь"
    ],
    "murmanskaya":[
      "Апатиты",
      "Гаджиево",
      "Заозерск",
      "Кировск",
      "Мончегорск",
      "Мурманск",
      "Оленегорск",
      "Оленегорск-1",
      "Оленегорск-2",
      "Островной",
      "Полярные",
      "Зори",
      "Полярный",
      "Североморск",
      "Снежногорск"
    ],
    "nizhegorodskaya":[
      "Арзамаc",
      "Бор",
      "Выкса",
      "Дзержинск",
      "Кулебаки",
      "Навашино",
      "Нижний",
      "Новгород",
      "Первомайск",
      "Перевоз",
      "Саров",
      "Семенов",
      "Шахунья"
    ],
    "novgorodskaya":[
      "Великий Новгород"
    ],
    "novosibirskaya":[
      "Бердск",
      "Искитим",
      "Кольцово",
      "Новосибирск",
      "Обь"
    ],
    "omskaya":[
      "Омск"
    ],
    "orenburskaya":[
      "Бугуруслан",
      "Бузулук",
      "Гай",
      "Кувандык",
      "Медногорск",
      "Новотроицк",
      "Оренбург",
      "Орск",
      "Сорочинск",
      "Ясный"
    ],
    "orlovskaya":[
      "Ливны",
      "Мценск",
      "Орёл"
    ],
    "pensenskaya":[
      "Ливны",
      "Мценск",
      "Орёл"
    ],
    "permskiy":[
      "Александровск",
      "Березники",
      "Гремячинск",
      "Губаха",
      "Добрянка",
      "Кизел",
      "Краснокамск",
      "Кудымкар",
      "Кунгур",
      "Лысьва",
      "Пермь",
      "Соликамск",
      "Чайковский",
      "Чусовой"
    ],
    "psovskaya":[
      "Великие Луки",
      "Псков"
    ],
    "rostovskya":[
      "Азов",
      "Батайск",
      "Волгодонск",
      "Гуково",
      "Донецк",
      "Зверево",
      "Каменск-Шахтинский",
      "Новочеркасск",
      "Новошахтинск",
      "Ростов-на-Дону",
      "Таганрог",
      "Шахты"
    ],
    "ryzanskaya":[
      "Касимов",
      "Рязань",
      "Сасово",
      "Скопин"
    ],
    "samarskaya":[
      "Жигулевск",
      "Кинель",
      "Новокуйбышевск",
      "Октябрьск",
      "Отрадный",
      "Похвистнево",
      "Самара",
      "Сызрань",
      "Тольятти",
      "Чапаевск"
    ],
    "saratovkaya":[
      "Аткарск",
      "Балаково",
      "Балашов",
      "Вольск",
      "Красноармейск",
      "Маркс",
      "Пугачев",
      "Ртищево",
      "Саратов",
      "Хвалынск",
      "Шиханы",
      "Энгельс"
    ],
    "sakhalinskaya":[
      "Южно-Сахалинск"
    ],
    "sverdlovskaya":[
      "Алапаевск",
      "Асбест",
      "Березовский",
      "Верхний Тагил",
      "Верхняя Пышма",
      "Верхняя Тура",
      "Волчанск",
      "Дегтярск",
      "Екатеринбург",
      "Заречный",
      "Ивдель",
      "Ирбит",
      "Каменск-Уральский",
      "Камышлов",
      "Карпинск",
      "Качканар",
      "Кировград",
      "Краснотурьинск",
      "Красноуральск",
      "Красноуфимск",
      "Кушва",
      "Лесной",
      "Малышев",
      "Нижний Тагил",
      "Нижняя Салда",
      "Нижняя Тура",
      "Новоуральск",
      "Первоуральск",
      "Полевской",
      "Ревда",
      "Североуральск",
      "Серов",
      "Среднеуральск"
    ],
    "smolenskaya":[
      "Десногорск",
      "Смоленск"
    ],
    "tamboskaya":[
      "Кирсанов",
      "Котовск",
      "Мичуринск",
      "Моршанск",
      "Рассказово",
      "Тамбов",
      "Уварово"
    ],
    "tverskaya":[
      "Андреаполь",
      "Белый",
      "Весьегонск",
      "Вышний",
      "Волочек",
      "Жарковский",
      "Западная",
      "Двина",
      "Зубцов",
      "Кашин",
      "Кесова",
      "Гора",
      "Кимры",
      "Красный",
      "Холм",
      "Лесное",
      "Село",
      "Лихославль",
      "Максатиха",
      "Молоково",
      "Нелидово",
      "Озерный",
      "Оленино",
      "Осташков",
      "Пено",
      "Рамешки",
      "Ржев",
      "Сандово",
      "Селижарово",
      "Сонково",
      "Спирово",
      "Старица",
      "Тверь",
      "Торжок",
      "Удомля"
    ],
    "tomskaya":[
      "Кедровый",
      "Северск",
      "Стрежевой",
      "Томск"
    ],
    "tulskaya":[
      "Донской",
      "Тула"
    ],
    "tumenskaya":[
      "Заводоуковск",
      "Ишим",
      "Тобольск",
      "Тюмень",
      "Ялуторовск"
    ],
    "ulyanovskaya":[
      "Димитровград",
      "Новоульяновск",
      "Ульяновск"
    ],
    "chelyabinskaya":[
      "Верхний Уфалей",
      "Златоуст",
      "Карабаш",
      "Копейск",
      "Коркино",
      "Кыштым",
      "Магнитогорск",
      "Миасс",
      "Озерск",
      "Снежинск",
      "Трехгорный",
      "Трехгорный-1",
      "Троицк",
      "Усть-Катав",
      "Чебаркуль",
      "Челябинск",
      "Южноуральск"
    ],
    "zabaykalskiy":[
      "Горный",
      "Чита"
    ],
    "yaroslavskaya":[
      "Переславль-Залесский",
      "Ярославль"
    ],
    "evreyskaya":[
      "Биробиджан"
    ],
    "zaporozhskaya":[
      "Бердянск",
      "Мелитополь",
      "Энергодар",
      "Горо"
    ],
    "сrimea":[
      "Алушта",
      "Армянск",
      "Джанкой",
      "Евпатория",
      "Керчь",
      "Красноперекопск",
      "Саки",
      "Симферополь",
      "Судак",
      "Феодосия",
      "Ялта"
    ],
    "lnr":[
      "Ровеньки",
      "Рубежное",
      "Северодонецк"
    ],
    "khersonskaya":[
      "Алёшки",
      "Белозёрка",
      "Берислав",
      "Великая",
      "Александровка",
      "Лепетиха",
      "Верхний",
      "Рогачик",
      "Высокополье",
      "Геническ",
      "Голая",
      "Пристань",
      "Горностаевка",
      "Ивановка",
      "Каланчак",
      "Каховка",
      "Нижние",
      "Серогозы",
      "Новая",
      "Нововоронцовка",
      "Новотроицкое",
      "Скадовск",
      "Снигирёвка",
      "Херсон",
      "Чаплинка"
    ]
  }